autorad/__init__.py
autorad/__main__.py
autorad/config/__init__.py
autorad/config/config.py
autorad/config/pyradiomics_feature_names.json
autorad/config/type_definitions.py
autorad/config/pyradiomics_params/CT_Baessler.yaml
autorad/config/pyradiomics_params/CT_default.yaml
autorad/config/pyradiomics_params/CT_default_feature_map.yaml
autorad/config/pyradiomics_params/MR_default.yaml
autorad/data/__init__.py
autorad/data/dataset.py
autorad/evaluation/__init__.py
autorad/evaluation/eval_utils.py
autorad/evaluation/evaluate.py
autorad/evaluation/metrics.py
autorad/external/__init__.py
autorad/external/delong.py
autorad/external/download_WORC.py
autorad/feature_extraction/__init__.py
autorad/feature_extraction/core.py
autorad/feature_extraction/extractor.py
autorad/feature_extraction/voxelbased.py
autorad/feature_selection/__init__.py
autorad/feature_selection/selector.py
autorad/inference/__init__.py
autorad/inference/infer.py
autorad/inference/infer_utils.py
autorad/models/__init__.py
autorad/models/classifier.py
autorad/models/optuna_params.py
autorad/preprocessing/__init__.py
autorad/preprocessing/oversample_utils.py
autorad/preprocessing/preprocess.py
autorad/registration/__init__.py
autorad/segmentation/__init__.py
autorad/segmentation/utils.py
autorad/training/__init__.py
autorad/training/optimizer.py
autorad/training/train_utils.py
autorad/training/trainer.py
autorad/utils/__init__.py
autorad/utils/conversion.py
autorad/utils/extraction_utils.py
autorad/utils/io.py
autorad/utils/mlflow_utils.py
autorad/utils/preprocessing.py
autorad/utils/spatial.py
autorad/utils/splitting.py
autorad/utils/statistics.py
autorad/utils/testing.py
autorad/utils/utils.py
autorad/visualization/__init__.py
autorad/visualization/matplotlib_utils.py
autorad/visualization/plot_volumes.py
autorad/visualization/plotly_utils.py
autorad/webapp/__init__.py
autorad/webapp/app.py
autorad/webapp/extraction_utils.py
autorad/webapp/extractor.py
autorad/webapp/paths_example.csv
autorad-0.2.6.dist-info/LICENSE
autorad-0.2.6.dist-info/METADATA
autorad-0.2.6.dist-info/WHEEL
autorad-0.2.6.dist-info/entry_points.txt
autorad-0.2.6.dist-info/top_level.txt
autorad-0.2.6.dist-info/RECORD
