Metadata-Version: 2.1
Name: autorad
Version: 0.2.6
Summary: Radiomics-related modules for extraction and experimenting
Home-page: https://github.com/pwoznicki/AutoRadiomics
Author: Piotr Woznicki
Author-email: piotr.a.woznicki@gmail.com
License: Apache 2.0
Project-URL: Bug Tracker, https://github.com/pwoznicki/AutoRadiomics
Classifier: Programming Language :: Python :: 3
Classifier: Operating System :: OS Independent
Requires-Python: >=3.9
License-File: LICENSE
Requires-Dist: pyradiomics (==3.0.1)
Requires-Dist: scikit-learn (==1.2.0)
Requires-Dist: SimpleITK (==2.1.1.2)
Requires-Dist: pandas (==1.4.2)
Requires-Dist: scipy (==1.9)
Requires-Dist: pyyaml (==6.0)
Requires-Dist: statsmodels (==0.13.2)
Requires-Dist: mlflow (==2.0.1)
Requires-Dist: nibabel (==3.2.1)
Requires-Dist: matplotlib (==3.5)
Requires-Dist: xnat (==0.4.2)
Requires-Dist: tqdm (==4.62.3)
Requires-Dist: pqdm (>=0.2.0)
Requires-Dist: Boruta (==0.3)
Requires-Dist: xgboost (==1.6.0)
Requires-Dist: imbalanced-learn (==0.9.1)
Requires-Dist: optuna (==2.10.0)
Requires-Dist: plotly (==5.5)
Requires-Dist: shap (==0.41)
Requires-Dist: scikit-image (==0.19)
Provides-Extra: app
Requires-Dist: streamlit (~=1.15) ; extra == 'app'
Requires-Dist: jupytext (~=1.14) ; extra == 'app'
Provides-Extra: dev
Requires-Dist: coverage (~=6.2) ; extra == 'dev'
Requires-Dist: great-expectations ; extra == 'dev'
Requires-Dist: pytest (~=6.2) ; extra == 'dev'
Requires-Dist: hypothesis (~=6.36) ; extra == 'dev'
Requires-Dist: black (~=22.10) ; extra == 'dev'
Requires-Dist: flake8 (~=4.0) ; extra == 'dev'
Requires-Dist: isort (~=5.10) ; extra == 'dev'
Requires-Dist: pre-commit (~=2.17) ; extra == 'dev'
Requires-Dist: streamlit (~=1.15) ; extra == 'dev'
Requires-Dist: jupytext (~=1.14) ; extra == 'dev'
Requires-Dist: mkdocs (==1.4.2) ; extra == 'dev'
Requires-Dist: mkdocs-material (==8.5.10) ; extra == 'dev'
Requires-Dist: mkdocstrings[python] (==0.19.0) ; extra == 'dev'
Provides-Extra: docs
Requires-Dist: mkdocs (==1.4.2) ; extra == 'docs'
Requires-Dist: mkdocs-material (==8.5.10) ; extra == 'docs'
Requires-Dist: mkdocstrings[python] (==0.19.0) ; extra == 'docs'
